githubtoolkit/__init__.py
githubtoolkit/__main__.py
githubtoolkit-1.0.2.dist-info/LICENSE.txt
githubtoolkit-1.0.2.dist-info/METADATA
githubtoolkit-1.0.2.dist-info/WHEEL
githubtoolkit-1.0.2.dist-info/top_level.txt
githubtoolkit-1.0.2.dist-info/RECORD
