Metadata-Version: 2.1
Name: githubtoolkit
Version: 1.0.2
Summary: some tools for working with GitHub
Author-email: Leander Kafemann <leander@kafemann.berlin>
Project-URL: Homepage, https://github.com/LeanderKafemann/githubtools
Classifier: Programming Language :: Python :: 3
Classifier: License :: OSI Approved :: MIT License
Classifier: Operating System :: OS Independent
Requires-Python: >=3.11
License-File: LICENSE.txt
Requires-Dist: requests
